<?xml version="1.0"?>
<!DOCTYPE hibernate-mapping PUBLIC "-//Hibernate/Hibernate Mapping DTD 3.0//EN"
"http://www.hibernate.org/dtd/hibernate-mapping-3.0.dtd">
<!-- Generated Jul 11, 2019 2:30:40 PM by Hibernate Tools 4.3.1 -->
<hibernate-mapping>
    <class name="com.vmmc.entities.Tblsetupdeliverymodes" table="tblsetupdeliverymodes" catalog="zimepms" optimistic-lock="version">
        <id name="deliveryModeId" type="string">
            <column name="DeliveryModeID" length="3" />
            <generator class="assigned" />
        </id>
        <property name="deliveryMode" type="string">
            <column name="DeliveryMode" />
        </property>
        <property name="category" type="string">
            <column name="Category" length="16" />
        </property>
    </class>
</hibernate-mapping>
